pattools/__init__.py
pattools/_timelinefilter.py
pattools/ants.py
pattools/fsl.py
pattools/image.py
pattools/interpolate.py
pattools/ms.py
pattools/pacs.py
pattools/resources.py
pattools/timelines.py
pattools-0.1.3.dist-info/LICENSE
pattools-0.1.3.dist-info/METADATA
pattools-0.1.3.dist-info/WHEEL
pattools-0.1.3.dist-info/top_level.txt
pattools-0.1.3.dist-info/RECORD
