Metadata-Version: 2.1
Name: pattools
Version: 0.1.3
Summary: Toolkit for neuro-imaging data manipulation and automation
Home-page: https://github.com/plwp/pat_tools
Author: plwp
Author-email: pat@plwp.net
License: UNKNOWN
Platform: UNKNOWN
Classifier: Programming Language :: Python :: 3
Classifier: License :: OSI Approved :: MIT License
Classifier: Operating System :: OS Independent
Requires-Python: >=3.6
Requires-Dist: pydicom
Requires-Dist: pynetdicom
Requires-Dist: dicom2nifti
Requires-Dist: requests
Requires-Dist: nibabel
Requires-Dist: clint
Requires-Dist: imageio
Requires-Dist: joblib
Requires-Dist: h5py
Requires-Dist: numpy
Requires-Dist: scikit-learn
Requires-Dist: scikit-image
